README.md
setup.py
github_wrapper/__init__.py
github_wrapper.egg-info/PKG-INFO
github_wrapper.egg-info/SOURCES.txt
github_wrapper.egg-info/dependency_links.txt
github_wrapper.egg-info/requires.txt
github_wrapper.egg-info/top_level.txt
github_wrapper/common/__init__.py
github_wrapper/common/authentitication.py
github_wrapper/common/pretty.py
github_wrapper/v3/__init__.py
github_wrapper/v3/issues/Issues.py
github_wrapper/v3/issues/Labels.py
github_wrapper/v3/issues/__init__.py
github_wrapper/v3/pull_requests/PullRequest.py
github_wrapper/v3/pull_requests/__init__.py
github_wrapper/v3/repositories/Branches.py
github_wrapper/v3/repositories/Repositories.py
github_wrapper/v3/repositories/__init__.py