Metadata-Version: 2.1
Name: github-wrapper
Version: 0.0.12
Summary: UNKNOWN
Home-page: https://github.com/py-nayls/github-wrapper
Author: Gagarin Svyatoslav
Author-email: nayls@bk.ru
Maintainer: Gagarin Svyatoslav
Maintainer-email: nayls@bk.ru
License: UNKNOWN
Platform: UNKNOWN
Classifier: Framework :: Pytest
Requires-Python: >=3.5
